MANIFEST.in
README.rst
setup.py
docs/HISTORY.txt
docs/LICENSE.GPL
docs/LICENSE.txt
ftw/__init__.py
ftw.casauth.egg-info/PKG-INFO
ftw.casauth.egg-info/SOURCES.txt
ftw.casauth.egg-info/dependency_links.txt
ftw.casauth.egg-info/entry_points.txt
ftw.casauth.egg-info/namespace_packages.txt
ftw.casauth.egg-info/not-zip-safe
ftw.casauth.egg-info/requires.txt
ftw.casauth.egg-info/top_level.txt
ftw/casauth/__init__.py
ftw/casauth/cas.py
ftw/casauth/configure.zcml
ftw/casauth/plugin.py
ftw/casauth/testing.py
ftw/casauth/restapi/__init__.py
ftw/casauth/restapi/caslogin.py
ftw/casauth/restapi/configure.zcml
ftw/casauth/tests/__init__.py
ftw/casauth/tests/test_browser.py
ftw/casauth/tests/test_cas.py
ftw/casauth/tests/test_plugin.py
ftw/casauth/tests/test_restapi.py
ftw/casauth/tests/utils.py
ftw/casauth/tests/data/service_validate_invalid_ticket.xml
ftw/casauth/tests/data/service_validate_success.xml
ftw/casauth/www/addPlugin.zpt
ftw/casauth/www/config.zpt