Metadata-Version: 2.1
Name: ftw.casauth
Version: 1.4.2
Summary: Plone PAS plugin for authentication against CAS.
Home-page: https://github.com/4teamwork/ftw.casauth
Author: Thomas Buchberger
Author-email: mailto:t.buchberger@4teamwork.ch
License: GPL2
Platform: UNKNOWN
Classifier: Framework :: Plone
Classifier: Framework :: Plone :: 4.3
Classifier: Framework :: Plone :: 5.1
Classifier: Programming Language :: Python
Classifier: Programming Language :: Python :: 2.7
Classifier: Intended Audience :: Developers
Classifier: Topic :: Software Development :: Libraries :: Python Modules
Provides-Extra: tests
